{
  "sections": {
    "hero": {
      "type": "hero",
      "blocks": {
        "button": {
          "type": "button",
          "settings": {
            "text": "Amène moi vers cette beauté →",
            "link": "shopify:\/\/collections\/shrink",
            "style": "border",
            "size": "normal",
            "color": "#ffffff"
          }
        }
      },
      "block_order": [
        "button"
      ],
      "settings": {
        "image": "shopify:\/\/shop_images\/220624_StudioHausen_0680_1.jpg",
        "video": "",
        "alignment": "h-center v-bottom",
        "overlay_color": "#fffbfb",
        "overlay_opacity": 0,
        "mobile_min_height": 600,
        "video_mobile": "",
        "expanded": false,
        "collapsed": false,
        "show_on_desktop": true,
        "show_on_mobile": true
      }
    },
    "1660555114671a82a1": {
      "type": "rich-text",
      "blocks": {
        "1660555114d02710bd-1": {
          "type": "subheading",
          "settings": {
            "text": "LES SENSATIONNELS",
            "max_width": 1650,
            "increase_space_before_block": true
          }
        }
      },
      "block_order": [
        "1660555114d02710bd-1"
      ],
      "settings": {
        "text_align": "center",
        "show_background": false,
        "expanded": true,
        "collapsed": false,
        "show_on_desktop": true,
        "show_on_mobile": true
      }
    },
    "featured-collection": {
      "type": "featured-collection",
      "settings": {
        "collection": "frontpage",
        "show_collection_title": false,
        "show_collection_description": false,
        "show_collection_image": false,
        "enable_filtering": false,
        "show_background": false,
        "expanded": false,
        "expanded_content": true,
        "collapsed": true,
        "show_on_desktop": true,
        "show_on_mobile": true
      }
    },
    "510fb3a3-fe77-4861-8e04-68cb1d67e4b7": {
      "type": "image-with-text",
      "blocks": {
        "template--15366539903023__510fb3a3-fe77-4861-8e04-68cb1d67e4b7-166550135557a50df3-0": {
          "type": "subheading",
          "settings": {
            "text": "Système d'étagères SHRINK  \/modulaire, extensible, individuel.",
            "increase_space_before_block": true
          }
        },
        "template--15366539903023__510fb3a3-fe77-4861-8e04-68cb1d67e4b7-166550135557a50df3-2": {
          "type": "paragraph",
          "settings": {
            "text": "<p><strong>1 MODÉLE <\/strong><\/p><p><strong>6 COULEURS<\/strong><\/p><p>Autant de combinaisons que vous le voulez.<\/p>",
            "increase_space_before_block": true
          }
        },
        "template--15366539903023__510fb3a3-fe77-4861-8e04-68cb1d67e4b7-166550135557a50df3-3": {
          "type": "button",
          "settings": {
            "text": "fais briller mon intérieur →",
            "link": "shopify:\/\/collections\/shrink",
            "style": "border",
            "size": "normal",
            "increase_space_before_block": true
          }
        }
      },
      "block_order": [
        "template--15366539903023__510fb3a3-fe77-4861-8e04-68cb1d67e4b7-166550135557a50df3-0",
        "template--15366539903023__510fb3a3-fe77-4861-8e04-68cb1d67e4b7-166550135557a50df3-2",
        "template--15366539903023__510fb3a3-fe77-4861-8e04-68cb1d67e4b7-166550135557a50df3-3"
      ],
      "settings": {
        "image": "shopify:\/\/shop_images\/ezgif.com-gif-maker.gif",
        "text_position": "right",
        "show_background": true,
        "expanded": false,
        "expanded_content": false,
        "collapsed": false,
        "show_on_desktop": true,
        "show_on_mobile": true
      }
    }
  },
  "order": [
    "hero",
    "1660555114671a82a1",
    "featured-collection",
    "510fb3a3-fe77-4861-8e04-68cb1d67e4b7"
  ]
}
